synesis/__init__.py
synesis/api.py
synesis/cli.py
synesis/compiler.py
synesis/error_handler.py
synesis/lsp_adapter.py
synesis/ast/__init__.py
synesis/ast/nodes.py
synesis/ast/results.py
synesis/exporters/__init__.py
synesis/exporters/csv_export.py
synesis/exporters/json_export.py
synesis/exporters/xls_export.py
synesis/grammar/__init__.py
synesis/grammar/synesis.lark
synesis/parser/__init__.py
synesis/parser/bib_loader.py
synesis/parser/error_handler.py
synesis/parser/lexer.py
synesis/parser/template_loader.py
synesis/parser/transformer.py
synesis/semantic/__init__.py
synesis/semantic/linker.py
synesis/semantic/validator.py
synesis-0.2.2.dist-info/licenses/LICENSE
synesis-0.2.2.dist-info/METADATA
synesis-0.2.2.dist-info/WHEEL
synesis-0.2.2.dist-info/entry_points.txt
synesis-0.2.2.dist-info/top_level.txt
synesis-0.2.2.dist-info/RECORD
