Metadata-Version: 2.4
Name: synesis
Version: 0.2.2
Summary: The confluence of information into intelligence - A DSL compiler that transforms qualitative research annotations into canonical knowledge structures
Author-email: "De Britto, Christian Maciel" <chriseana@gmail.com>
Maintainer-email: Synesis Language Organization <synesis-lang@users.noreply.github.com>
License-Expression: MIT
Project-URL: Homepage, https://synesis-lang.github.io/synesis-docs
Project-URL: Documentation, https://synesis-lang.github.io/synesis-docs
Project-URL: Repository, https://github.com/synesis-lang/synesis
Project-URL: Issues, https://github.com/synesis-lang/synesis/issues
Project-URL: Changelog, https://github.com/synesis-lang/synesis/blob/main/CHANGELOG.md
Keywords: qualitative-research,compiler,dsl,domain-specific-language,bibliometrics,annotation,research-tools,bibtex,ontology
Classifier: Development Status :: 4 - Beta
Classifier: Intended Audience :: Science/Research
Classifier: Intended Audience :: Developers
Classifier: Programming Language :: Python :: 3
Classifier: Programming Language :: Python :: 3.10
Classifier: Programming Language :: Python :: 3.11
Classifier: Programming Language :: Python :: 3.12
Classifier: Topic :: Text Processing :: Markup
Classifier: Topic :: Software Development :: Compilers
Classifier: Topic :: Scientific/Engineering
Classifier: Operating System :: OS Independent
Classifier: Typing :: Typed
Requires-Python: >=3.10
License-File: LICENSE
Requires-Dist: lark>=1.1
Requires-Dist: bibtexparser>=1.4
Requires-Dist: regex>=2023.0.0
Requires-Dist: click>=8.0
Requires-Dist: openpyxl>=3.0
Provides-Extra: dev
Requires-Dist: pytest>=7.0; extra == "dev"
Requires-Dist: pytest-cov>=4.0; extra == "dev"
Requires-Dist: build>=0.10; extra == "dev"
Requires-Dist: twine>=4.0; extra == "dev"
Dynamic: license-file
